pytest_eth/__init__.py
pytest_eth/account.py
pytest_eth/config.py
pytest_eth/factory.py
pytest_eth/handler.py
pytest_eth/instance.py
pytest_eth/interfaces.py
pytest_eth/log.py
pytest_eth/tester.py
pytest_eth/utils.py
pytest_eth-0.0.0.dev1.dist-info/LICENSE
pytest_eth-0.0.0.dev1.dist-info/METADATA
pytest_eth-0.0.0.dev1.dist-info/WHEEL
pytest_eth-0.0.0.dev1.dist-info/entry_points.txt
pytest_eth-0.0.0.dev1.dist-info/top_level.txt
pytest_eth-0.0.0.dev1.dist-info/RECORD
