Metadata-Version: 2.1
Name: pytest-eth
Version: 0.0.0.dev1
Summary: PyTest plugin for testing Smart Contracts for Ethereum Virtual Machine (EVM).
Home-page: https://github.com/meherett/pytest-eth
Author: Meheret Tesfaye
Author-email: meherett@zoho.com
License: MIT
Platform: UNKNOWN
Classifier: Development Status :: 1 - Planning
Classifier: License :: OSI Approved :: MIT License
Classifier: Programming Language :: Python :: 3.6
Classifier: Programming Language :: Python :: 3.7
Classifier: Framework :: Pytest
Requires-Python: >=3.6,<4
